{
  "signal": [
    {
      "name": "clk",
      "wave": "p.................."
    },
    {
      "name": "rx_valid_out",
      "wave": "0.1...............0"
    },
    {},
    {
      "name": "bit_idx",
      "wave": "=..================",
      "data": [
        "0",
        "2",
        "4",
        "6",
        "8",
        "10",
        "12",
        "14",
        "16",
        "18",
        "20",
        "22",
        "24",
        "26",
        "28",
        "30",
        "32"
      ]
    },
    {
      "name": "decoded[31:0]",
      "wave": "=..==..==..==..==..",
      "data": [
        "0x00000000",
        "0x00000003",
        "0x0000000F",
        "0x0000030F",
        "0x00000F0F",
        "0x00030F0F",
        "0x000F0F0F",
        "0x030F0F0F",
        "0x0F0F0F0F"
      ]
    }
  ],
  "head": {
    "text": "TB capture FSM \u2014 bit_idx grows 0->32, decoded fills to 0x0F0F0F0F",
    "tick": -15
  },
  "config": {
    "hscale": 2.5
  }
}